Workbook

Sheet Start Here
B2: KUBO CA PHE
B3: POS setup worksheet
B5: What this is | C5: This is everything the app needs to know about your coffee business. You do not have to finish it in one go, and you do not have to finish it at all — every one of these can also be typed straight into the app once it is on your phone. This sheet just makes it easier to gather, especially the recipe and cost pages, which are much simpler to work out with a scale on the counter than with a phone in your hand.
B7: Fill it in this order
B8: 1 · Menu & Prices | C8: Start here. Most of it is already filled in from your menu card — you mainly need to answer the size question.
B9: 2 · Customisations | C9: Milk, ice, sweetness, syrups, extras — and what each one costs the customer.
B10: 3 · Drink Rules | C10: Which of those choices each drink actually offers, and what is picked by default.
B11: 4 · Ingredients | C11: Everything you buy, including cups and lids. What you pay, and when to reorder.
B12: 5 · Recipes | C12: What goes into each drink. This is the big one — take your time.
B13: 6 · Suppliers | C13: Who you buy from. Quick.
B14: 7 · Business Setup | C14: Name, hours, order numbers. Two minutes.
B15: 8 · Your Questions | C15: Anything you want to ask, or anything the sheet did not cover.
B17: What the colours mean
B18: Please fill this in | C18: Yellow cells are the ones waiting on you.
B19: Already known — just check | C19: Taken straight off your menu card. Correct it if I read it wrong.
B20: Worked out for you | C20: Green cells calculate themselves — cost, profit and margin. Do not type in these.
B21: Example row | C21: Grey italic rows show the format expected. Delete them, or type over them.
B24: The one thing to decide first | C24: Your menu card shows ONE size for each drink — 16oz for everything except Vietnamese Coffee, which is 12oz. The plan I was given assumed two sizes (Small 12oz and Grande 16oz) on every drink. Those do not match, so sheet 1 asks you which is true. If it really is one size per drink, the app skips the size step entirely and every order is one tap faster.
B26: Nothing is invented | C26: No price, recipe quantity or ingredient cost in this workbook was made up. Everything already filled in came off your menu card. Everything else is blank, waiting for your real numbers.

Sheet 1 - Menu & Prices
A1: Menu & prices
A2: Grey rows are read off your menu card — please just check them. The yellow rows are for a second size, IF you want one: fill the price and I will add it, leave the whole row blank and that drink stays one size only. The green columns fill themselves once you have done the Recipes sheet.
A4: Category | B4: Drink | C4: Size name | D4: oz | E4: Price ₱ | F4: Recipe cost ₱ | G4: Gross profit ₱ | H4: Margin % | I4: On the menu? | J4: Description | K4: Your notes
A5: Classics | B5: Black | C5: Grande | D5: 16 | E5: 129 | F5: =IFERROR(SUMIFS('5 - Recipes'!$G$5:$G$80,'5 - Recipes'!$A$5:$A$80,$B5,'5 - Recipes'!$B$5:$B$80,$C5),0) | G5: =IF($E5="","",$E5-$F5) | H5: =IF(OR($E5="",$E5=0),"",$G5/$E5) | I5: Yes | J5: Phin-brewed coffee served black. Bold, smooth and clean.
A6: Classics | B6: Black | C6: Small | D6: 12 | F6: =IFERROR(SUMIFS('5 - Recipes'!$G$5:$G$80,'5 - Recipes'!$A$5:$A$80,$B6,'5 - Recipes'!$B$5:$B$80,$C6),0) | G6: =IF($E6="","",$E6-$F6) | H6: =IF(OR($E6="",$E6=0),"",$G6/$E6)
A7: Classics | B7: Spanish Latte | C7: Grande | D7: 16 | E7: 139 | F7: =IFERROR(SUMIFS('5 - Recipes'!$G$5:$G$80,'5 - Recipes'!$A$5:$A$80,$B7,'5 - Recipes'!$B$5:$B$80,$C7),0) | G7: =IF($E7="","",$E7-$F7) | H7: =IF(OR($E7="",$E7=0),"",$G7/$E7) | I7: Yes | J7: Bold phin coffee with creamy milk and a touch of sweetness.
A8: Classics | B8: Spanish Latte | C8: Small | D8: 12 | F8: =IFERROR(SUMIFS('5 - Recipes'!$G$5:$G$80,'5 - Recipes'!$A$5:$A$80,$B8,'5 - Recipes'!$B$5:$B$80,$C8),0) | G8: =IF($E8="","",$E8-$F8) | H8: =IF(OR($E8="",$E8=0),"",$G8/$E8)
A9: Classics | B9: Caramel Macchiato with Cold Foam | C9: Grande | D9: 16 | E9: 139 | F9: =IFERROR(SUMIFS('5 - Recipes'!$G$5:$G$80,'5 - Recipes'!$A$5:$A$80,$B9,'5 - Recipes'!$B$5:$B$80,$C9),0) | G9: =IF($E9="","",$E9-$F9) | H9: =IF(OR($E9="",$E9=0),"",$G9/$E9) | I9: Yes | J9: Smooth milk, vanilla and caramel with our signature cold foam.
A10: Classics | B10: Caramel Macchiato with Cold Foam | C10: Small | D10: 12 | F10: =IFERROR(SUMIFS('5 - Recipes'!$G$5:$G$80,'5 - Recipes'!$A$5:$A$80,$B10,'5 - Recipes'!$B$5:$B$80,$C10),0) | G10: =IF($E10="","",$E10-$F10) | H10: =IF(OR($E10="",$E10=0),"",$G10/$E10)
A11: Classics | B11: Matcha Latte | C11: Grande | D11: 16 | E11: 139 | F11: =IFERROR(SUMIFS('5 - Recipes'!$G$5:$G$80,'5 - Recipes'!$A$5:$A$80,$B11,'5 - Recipes'!$B$5:$B$80,$C11),0) | G11: =IF($E11="","",$E11-$F11) | H11: =IF(OR($E11="",$E11=0),"",$G11/$E11) | I11: Yes | J11: Vibrant matcha with creamy milk. Smooth, earthy and lightly sweet.
A12: Classics | B12: Matcha Latte | C12: Small | D12: 12 | F12: =IFERROR(SUMIFS('5 - Recipes'!$G$5:$G$80,'5 - Recipes'!$A$5:$A$80,$B12,'5 - Recipes'!$B$5:$B$80,$C12),0) | G12: =IF($E12="","",$E12-$F12) | H12: =IF(OR($E12="",$E12=0),"",$G12/$E12)
A13: Specialty Coffee | B13: Vietnamese Coffee | C13: Small | D13: 12 | E13: 129 | F13: =IFERROR(SUMIFS('5 - Recipes'!$G$5:$G$80,'5 - Recipes'!$A$5:$A$80,$B13,'5 - Recipes'!$B$5:$B$80,$C13),0) | G13: =IF($E13="","",$E13-$F13) | H13: =IF(OR($E13="",$E13=0),"",$G13/$E13) | I13: Yes | J13: Traditional phin coffee with sweetened condensed milk. Strong, bold and comforting.
A14: Specialty Coffee | B14: Vietnamese Coffee | C14: Grande | D14: 16 | F14: =IFERROR(SUMIFS('5 - Recipes'!$G$5:$G$80,'5 - Recipes'!$A$5:$A$80,$B14,'5 - Recipes'!$B$5:$B$80,$C14),0) | G14: =IF($E14="","",$E14-$F14) | H14: =IF(OR($E14="",$E14=0),"",$G14/$E14)
A15: Specialty Coffee | B15: Vietnamese Sea Salt Cream | C15: Grande | D15: 16 | E15: 159 | F15: =IFERROR(SUMIFS('5 - Recipes'!$G$5:$G$80,'5 - Recipes'!$A$5:$A$80,$B15,'5 - Recipes'!$B$5:$B$80,$C15),0) | G15: =IF($E15="","",$E15-$F15) | H15: =IF(OR($E15="",$E15=0),"",$G15/$E15) | I15: Yes | J15: Strong phin coffee with smooth sea salt cream. Rich, creamy and perfectly balanced.
A16: Specialty Coffee | B16: Vietnamese Sea Salt Cream | C16: Small | D16: 12 | F16: =IFERROR(SUMIFS('5 - Recipes'!$G$5:$G$80,'5 - Recipes'!$A$5:$A$80,$B16,'5 - Recipes'!$B$5:$B$80,$C16),0) | G16: =IF($E16="","",$E16-$F16) | H16: =IF(OR($E16="",$E16=0),"",$G16/$E16)
A17: Specialty Coffee | B17: Vietnamese Egg Coffee | C17: Grande | D17: 16 | E17: 159 | F17: =IFERROR(SUMIFS('5 - Recipes'!$G$5:$G$80,'5 - Recipes'!$A$5:$A$80,$B17,'5 - Recipes'!$B$5:$B$80,$C17),0) | G17: =IF($E17="","",$E17-$F17) | H17: =IF(OR($E17="",$E17=0),"",$G17/$E17) | I17: Yes | J17: Classic Hanoi-style egg coffee. Creamy, velvety and deliciously indulgent.
A18: Specialty Coffee | B18: Vietnamese Egg Coffee | C18: Small | D18: 12 | F18: =IFERROR(SUMIFS('5 - Recipes'!$G$5:$G$80,'5 - Recipes'!$A$5:$A$80,$B18,'5 - Recipes'!$B$5:$B$80,$C18),0) | G18: =IF($E18="","",$E18-$F18) | H18: =IF(OR($E18="",$E18=0),"",$G18/$E18)
A20: Q1 Sizes — which is true?
A21: A. One size per drink, exactly as printed on the card. Leave every yellow price row blank. The app drops the size step.
A22: B. Two sizes on everything. Fill a price in each yellow row.
A23: C. A mix. Fill only the yellow rows you actually sell, leave the rest blank.
A25: Your answer (A, B or C):
A27: Q2 Anything missing from the menu? Seasonal drinks, non-coffee, pastries — add them as new rows above.

Sheet 2 - Customisations
A1: Customisations
A2: Every choice a customer can make, and what it adds to the price. "Add Sea Salt Cream +20" is the only one printed on your card, so it is the only one filled in. For all the rest: put 0 if it is free, a number if you charge for it, or delete the row if you do not offer it at all. Add rows for anything I have missed.
A4: Group | B4: Choice | C4: Adds to price ₱ | D4: Pick one, or many? | E4: Must the customer choose? | F4: Show it in this order | G4: Still offered? | H4: Your notes
A5: Milk | B5: Full Cream | D5: Pick one | E5: Yes | F5: 1 | G5: Yes
A6: Milk | B6: Low Fat | D6: Pick one | E6: Yes | F6: 2 | G6: Yes
A7: Milk | B7: Skimmed | D7: Pick one | E7: Yes | F7: 3 | G7: Yes
A8: Milk | B8: Oat | D8: Pick one | E8: Yes | F8: 4 | G8: Yes
A9: Milk | B9: Coconut | D9: Pick one | E9: Yes | F9: 5 | G9: Yes
A11: Ice | B11: Regular | D11: Pick one | E11: Yes | F11: 1 | G11: Yes
A12: Ice | B12: Less Ice | D12: Pick one | E12: Yes | F12: 2 | G12: Yes
A13: Ice | B13: Extra Ice | D13: Pick one | E13: Yes | F13: 3 | G13: Yes
A14: Ice | B14: No Ice | D14: Pick one | E14: Yes | F14: 4 | G14: Yes
A16: Sweetness | B16: Regular | D16: Pick one | E16: Yes | F16: 1 | G16: Yes
A17: Sweetness | B17: Less Sweet | D17: Pick one | E17: Yes | F17: 2 | G17: Yes
A18: Sweetness | B18: No Sugar | D18: Pick one | E18: Yes | F18: 3 | G18: Yes
... A29: Sauce | B29: Caramel | D29: Pick one | E29: No | F29: 4 | G29: Yes
A31: Extras | B31: Sea Salt Cream | C31: 20 | D31: Pick any number | E31: No | F31: 1 | G31: Yes | H31: From your menu card: "Add Sea Salt Cream +20"
A32: Extras | B32: Extra Shot | D32: Pick any number | E32: No | F32: 2 | G32: Yes
A33: Extras | B33: Extra Syrup | D33: Pick any number | E33: No | F33: 3 | G33: Yes
A34: Extras | B34: Extra Sauce | D34: Pick any number | E34: No | F34: 4 | G34: Yes
A35: Extras | B35: Cold Foam | D35: Pick any number | E35: No | F35: 5 | G35: Yes
A38: Q3 Is "Add Sea Salt Cream +20" available on all four Classics, or only on Matcha Latte where it is printed?
A41: Q4 Are these really the milks you stock? Cross out any you do not carry, add any I have missed.

Sheet 3 - Drink Rules
A1: What each drink offers
A2: Not every drink should show every choice — Black is served black, so it probably needs no milk options at all. Put Yes or No in each column, and in the last columns write what should already be selected when the drink is tapped. Defaults are what make an order fast: if the usual setup is right, she taps the drink and adds it.
A4: Drink | B4: Show milk? | C4: Show ice? | D4: Show sweetness? | E4: Show syrup? | F4: Show sauce? | G4: Show extras? | H4: Default milk | I4: Default ice | J4: Default sweetness
A5: Black
A6: Spanish Latte
A7: Caramel Macchiato with Cold Foam
A8: Matcha Latte
A9: Vietnamese Coffee
A10: Vietnamese Sea Salt Cream
A11: Vietnamese Egg Coffee
A13: Black (example — delete or type over) | B13: No | C13: Yes | D13: No | E13: No | F13: No | G13: No | H13: — | I13: Regular | J13: —
A15: Q5 Any drink where a choice should be offered but priced differently from sheet 2? Note it here.

Sheet 4 - Ingredients
A1: Everything you buy
A2: Coffee, milk, syrups, matcha, condensed milk, eggs, salt, sugar — and packaging too: cups, lids, straws, sleeves. Column G works out what one gram, millilitre or piece costs you, and the Recipes sheet uses it to price each drink. The two example rows show the format — type over them.
A4: Ingredient | B4: What kind | C4: Measured in | D4: You buy it by the | E4: How much is in one of those | F4: What you pay for one ₱ | G4: Cost per g / ml / piece ₱ | H4: Track the stock? | I4: Reorder when below | J4: Panic when below | K4: How much you have now | L4: Supplier | M4: Your notes
A5: Coffee beans (example — type over) | B5: Coffee | C5: g | D5: kg | E5: 1000 | F5: 1200 | G5: =IF(OR($E5="",$E5=0),"",$F5/$E5) | H5: Yes | I5: 2000 | J5: 1000 | K5: 5000 | M5: 1 kg bag
A6: Grande cup 16oz (example — type over) | B6: Packaging | C6: pcs | D6: pack | E6: 50 | F6: 250 | G6: =IF(OR($E6="",$E6=0),"",$F6/$E6) | H6: Yes | I6: 100 | J6: 50 | K6: 300 | M6: 50 per pack
G7: =IF(OR($E7="",$E7=0),"",$F7/$E7)
G8: =IF(OR($E8="",$E8=0),"",$F8/$E8)
G9: =IF(OR($E9="",$E9=0),"",$F9/$E9)
G10: =IF(OR($E10="",$E10=0),"",$F10/$E10)
G11: =IF(OR($E11="",$E11=0),"",$F11/$E11)
G12: =IF(OR($E12="",$E12=0),"",$F12/$E12)
G13: =IF(OR($E13="",$E13=0),"",$F13/$E13)
G14: =IF(OR($E14="",$E14=0),"",$F14/$E14)
G15: =IF(OR($E15="",$E15=0),"",$F15/$E15)
G16: =IF(OR($E16="",$E16=0),"",$F16/$E16)
G17: =IF(OR($E17="",$E17=0),"",$F17/$E17)
G18: =IF(OR($E18="",$E18=0),"",$F18/$E18)
... G54: =IF(OR($E54="",$E54=0),"",$F54/$E54)
A56: Measured in — use g for anything you weigh, ml for anything you pour, pcs for anything you count (cups, lids, eggs).
A57: How much is in one — in that same unit. A 1 kg bag of beans is 1000 (g). A 1 L carton is 1000 (ml). A 50-pack of cups is 50 (pcs).
A58: Track the stock — say No for things made fresh daily, like ice. The app will still cost them, it just will not count them down.
A59: Reorder / panic — also in that same unit. "Reorder when below 2000 g" means when under 2 kg of beans are left.

Sheet 5 - Recipes
A1: What goes into each drink
A2: One line per ingredient per drink. Include the cup and the lid — they cost money too. Column G prices each line from sheet 4 and adds it up on the Menu sheet, so you can watch your margin as you fill this in. IMPORTANT: if you sell two sizes, each size gets its own lines. A Grande is never just "a Small times two".
A4: Drink | B4: Size name | C4: Ingredient | D4: How much | E4: Unit | F4: — | G4: Cost of this much ₱ | H4: Your notes
A5: Spanish Latte (example — type over) | B5: Grande | C5: Coffee beans | D5: 18 | E5: g | G5: =IFERROR($D5*INDEX('4 - Ingredients'!$G$5:$G$54,MATCH($C5,'4 - Ingredients'!$A$5:$A$54,0)),0) | H5: Two phin brews
A6: Spanish Latte (example — type over) | B6: Grande | C6: Grande cup 16oz | D6: 1 | E6: pcs | G6: =IFERROR($D6*INDEX('4 - Ingredients'!$G$5:$G$54,MATCH($C6,'4 - Ingredients'!$A$5:$A$54,0)),0)
A7: Black | G7: =IFERROR($D7*INDEX('4 - Ingredients'!$G$5:$G$54,MATCH($C7,'4 - Ingredients'!$A$5:$A$54,0)),0)
A8: Black | G8: =IFERROR($D8*INDEX('4 - Ingredients'!$G$5:$G$54,MATCH($C8,'4 - Ingredients'!$A$5:$A$54,0)),0)
A9: Black | G9: =IFERROR($D9*INDEX('4 - Ingredients'!$G$5:$G$54,MATCH($C9,'4 - Ingredients'!$A$5:$A$54,0)),0)
A10: Black | G10: =IFERROR($D10*INDEX('4 - Ingredients'!$G$5:$G$54,MATCH($C10,'4 - Ingredients'!$A$5:$A$54,0)),0)
A11: Black | G11: =IFERROR($D11*INDEX('4 - Ingredients'!$G$5:$G$54,MATCH($C11,'4 - Ingredients'!$A$5:$A$54,0)),0)
A12: Black | G12: =IFERROR($D12*INDEX('4 - Ingredients'!$G$5:$G$54,MATCH($C12,'4 - Ingredients'!$A$5:$A$54,0)),0)
A13: Black | G13: =IFERROR($D13*INDEX('4 - Ingredients'!$G$5:$G$54,MATCH($C13,'4 - Ingredients'!$A$5:$A$54,0)),0)
A14: Black | G14: =IFERROR($D14*INDEX('4 - Ingredients'!$G$5:$G$54,MATCH($C14,'4 - Ingredients'!$A$5:$A$54,0)),0)
A16: Spanish Latte | G16: =IFERROR($D16*INDEX('4 - Ingredients'!$G$5:$G$54,MATCH($C16,'4 - Ingredients'!$A$5:$A$54,0)),0)
A17: Spanish Latte | G17: =IFERROR($D17*INDEX('4 - Ingredients'!$G$5:$G$54,MATCH($C17,'4 - Ingredients'!$A$5:$A$54,0)),0)
A18: Spanish Latte | G18: =IFERROR($D18*INDEX('4 - Ingredients'!$G$5:$G$54,MATCH($C18,'4 - Ingredients'!$A$5:$A$54,0)),0)
A19: Spanish Latte | G19: =IFERROR($D19*INDEX('4 - Ingredients'!$G$5:$G$54,MATCH($C19,'4 - Ingredients'!$A$5:$A$54,0)),0)
... A68: Vietnamese Egg Coffee | G68: =IFERROR($D68*INDEX('4 - Ingredients'!$G$5:$G$54,MATCH($C68,'4 - Ingredients'!$A$5:$A$54,0)),0)
A71: Ingredient names must match sheet 4 exactly, or the cost will show as ₱0.00.
A72: Ran out of lines for a drink? Insert more rows — just copy an existing row so the cost formula comes with it.

Sheet 6 - Suppliers
A1: Who you buy from
A2: Only what you need to reorder. Skip anything you do not track.
A4: Supplier | B4: Contact person | C4: Phone / Viber / page | D4: What you buy from them | E4: Your notes
A5: Bean roaster (example — type over) | B5: Ate Jen | C5: 0917 000 0000 | D5: Coffee beans | E5: Delivers Tuesdays

Sheet 7 - Business Setup
A1: Business setup
A2: Two minutes. These are all changeable in the app afterwards, so a rough answer is fine.
A4: Business name, exactly as it should print on reports | C4: e.g. Kubo Cà Phê
A5: What time do you usually open? | C5: For the daily totals
A6: What time do you usually close?
A7: If you sell at 12:30am, which day should it count as? | C7: Most shops say "the day before". This sets when the trading day rolls over.
A8: Order numbers — plain 0001, or with a letter in front? | C8: e.g. K-0001
A9: Should order numbers start again from 1 each day? | C9: Yes or No
A10: Do you want the customer name shown on the order screen? | C10: Yes or No
A11: Cash and GCash only, for now? | C11: Yes or No — anything else and tell me what
A12: Do you ever give discounts? | C12: Not built yet, but tell me if you will need it
A13: Do you want a receipt at all — printed, or sent? | C13: Not built in this version; asking for later
A14: Roughly how many drinks on a normal day? | C14: Helps me size things sensibly
A15: Roughly how many on your busiest day?

Sheet 8 - Your Questions
A1: Over to you
A2: Anything the sheet did not ask about, anything you want the app to do, anything that annoys you about how you work now. Write it however you like — rough is fine, and nothing here is a commitment.
A4: What takes the longest when you are serving someone?
A5: What do you currently write down on paper?
A6: What do you most often forget to record?
A7: Which numbers do you actually want to see at the end of a day?
A8: Is there anything on the menu that is fiddly to ring up?
A9: Anything you want the app to do that I have not mentioned?
A10: Anything you want it NOT to do?
A11: Anything else — write freely
